spider_env/__init__.py
spider_env/spider_env.py
spider_env_custom-0.1.0.dist-info/METADATA
spider_env_custom-0.1.0.dist-info/WHEEL
spider_env_custom-0.1.0.dist-info/top_level.txt
spider_env_custom-0.1.0.dist-info/RECORD
