Metadata-Version: 2.4
Name: spider_env_custom
Version: 0.1.0
Summary: Environment wrapper for the Spider dataset
Author: Kha Nguyen Van
Author-email: vankha.contact@gmail.com
Classifier: Programming Language :: Python :: 3
Classifier: Operating System :: OS Independent
Requires-Python: >=3.8
Requires-Dist: numpy==1.26.4
Dynamic: author
Dynamic: author-email
Dynamic: classifier
Dynamic: description
Dynamic: description-content-type
Dynamic: requires-dist
Dynamic: requires-python
Dynamic: summary
